{
    "RowStruct": "/Script/Icarus.BestiaryTraitType",
    "Defaults": {
        "Color": {
            "R": 0,
            "G": 0,
            "B": 0,
            "A": 0
        },
        "Icon": "None"
    },
    "Rows": [
        {
            "Name": "Weakness",
            "Color": {
                "R": 0.7135419845581055,
                "G": 0.1740719974040985,
                "B": 0.10405799746513367,
                "A": 1
            },
            "Icon": "/Game/Assets/2DArt/UI/Icons/Icon_Equipment.Icon_Equipment"
        },
        {
            "Name": "CritSpot",
            "Color": {
                "R": 0.42708298563957214,
                "G": 0.024181000888347626,
                "A": 1
            },
            "Icon": "/Game/Assets/2DArt/UI/Icons/Icon_Crit.Icon_Crit"
        },
        {
            "Name": "Strength",
            "Color": {
                "R": 0.01305299997329712,
                "G": 0.09014599770307541,
                "B": 0.23958300054073334,
                "A": 1
            },
            "Icon": "/Game/Assets/2DArt/UI/Icons/Icon_StrongCritPoint.Icon_StrongCritPoint"
        },
        {
            "Name": "Behavior",
            "Color": {
                "R": 0.21326099336147308,
                "G": 0.25,
                "B": 0.1497649997472763,
                "A": 1
            },
            "Icon": "/Game/Assets/2DArt/UI/Icons/Icon_ConcussionDebuff.Icon_ConcussionDebuff"
        },
        {
            "Name": "DamageType",
            "Color": {
                "R": 0.3682990074157715,
                "G": 0.10980899631977081,
                "B": 0.45833298563957214,
                "A": 1
            },
            "Icon": "/Game/Assets/2DArt/UI/Icons/Icon_Combat.Icon_Combat"
        }
    ]
}